odoo/addons/helpdesk_mgmt/README.rst
odoo/addons/helpdesk_mgmt/__init__.py
odoo/addons/helpdesk_mgmt/__manifest__.py
odoo/addons/helpdesk_mgmt/controllers/__init__.py
odoo/addons/helpdesk_mgmt/controllers/main.py
odoo/addons/helpdesk_mgmt/controllers/myaccount.py
odoo/addons/helpdesk_mgmt/data/helpdesk_data.xml
odoo/addons/helpdesk_mgmt/demo/helpdesk_demo.xml
odoo/addons/helpdesk_mgmt/i18n/es.po
odoo/addons/helpdesk_mgmt/i18n/helpdesk_mgmt.pot
odoo/addons/helpdesk_mgmt/i18n/pt_BR.po
odoo/addons/helpdesk_mgmt/migrations/11.0.1.10.1/post-migrate.py
odoo/addons/helpdesk_mgmt/models/__init__.py
odoo/addons/helpdesk_mgmt/models/helpdesk_ticket.py
odoo/addons/helpdesk_mgmt/models/helpdesk_ticket_category.py
odoo/addons/helpdesk_mgmt/models/helpdesk_ticket_channel.py
odoo/addons/helpdesk_mgmt/models/helpdesk_ticket_stage.py
odoo/addons/helpdesk_mgmt/models/helpdesk_ticket_tag.py
odoo/addons/helpdesk_mgmt/models/helpdesk_ticket_team.py
odoo/addons/helpdesk_mgmt/models/res_partner.py
odoo/addons/helpdesk_mgmt/readme/CONFIGURE.rst
odoo/addons/helpdesk_mgmt/readme/CONTRIBUTORS.rst
odoo/addons/helpdesk_mgmt/readme/DESCRIPTION.rst
odoo/addons/helpdesk_mgmt/readme/USAGE.rst
odoo/addons/helpdesk_mgmt/security/helpdesk_security.xml
odoo/addons/helpdesk_mgmt/security/ir.model.access.csv
odoo/addons/helpdesk_mgmt/static/description/Categories.PNG
odoo/addons/helpdesk_mgmt/static/description/Channels.PNG
odoo/addons/helpdesk_mgmt/static/description/Stage.PNG
odoo/addons/helpdesk_mgmt/static/description/Tags.PNG
odoo/addons/helpdesk_mgmt/static/description/Teams.PNG
odoo/addons/helpdesk_mgmt/static/description/Tickets01.PNG
odoo/addons/helpdesk_mgmt/static/description/Tickets02.PNG
odoo/addons/helpdesk_mgmt/static/description/Tickets03.PNG
odoo/addons/helpdesk_mgmt/static/description/Tickets_Kanban.PNG
odoo/addons/helpdesk_mgmt/static/description/helpdesk.svg
odoo/addons/helpdesk_mgmt/static/description/icon.png
odoo/addons/helpdesk_mgmt/static/description/index.html
odoo11_addon_helpdesk_mgmt-11.0.1.12.0.dist-info/METADATA
odoo11_addon_helpdesk_mgmt-11.0.1.12.0.dist-info/WHEEL
odoo11_addon_helpdesk_mgmt-11.0.1.12.0.dist-info/top_level.txt
odoo11_addon_helpdesk_mgmt-11.0.1.12.0.dist-info/RECORD
